NEExT/__init__.py
NEExT/framework.py
NEExT/helper_functions.py
NEExT/io.py
NEExT/builders/__init__.py
NEExT/builders/embedding_builder.py
NEExT/collections/__init__.py
NEExT/collections/egonet_collection.py
NEExT/collections/graph_collection.py
NEExT/datasets/__init__.py
NEExT/datasets/graph_dataset.py
NEExT/embeddings/__init__.py
NEExT/embeddings/embeddings.py
NEExT/embeddings/graph_embeddings.py
NEExT/features/__init__.py
NEExT/features/features.py
NEExT/features/node_features.py
NEExT/features/structural_node_features.py
NEExT/graphs/__init__.py
NEExT/graphs/egonet.py
NEExT/graphs/graph.py
NEExT/ml_models/__init__.py
NEExT/ml_models/feature_importance.py
NEExT/ml_models/ml_models.py
NEExT/outliers/__init__.py
NEExT/outliers/cosine_outlier_detector.py
NEExT/outliers/lgbm_outlier.py
NEExT/outliers/benchmark_utils/__init__.py
NEExT/outliers/benchmark_utils/data_loading.py
NEExT/outliers/benchmark_utils/embed.py
NEExT/outliers/benchmark_utils/models.py
NEExT/outliers/benchmark_utils/supervised.py
NEExT/outliers/benchmark_utils/unsupervised.py
neext-0.2.10.dist-info/METADATA
neext-0.2.10.dist-info/WHEEL
neext-0.2.10.dist-info/licenses/LICENSE
neext-0.2.10.dist-info/RECORD
