Metadata-Version: 2.4
Name: NEExT
Version: 0.2.10
Summary: Network Embedding Experimentation Toolkit - A powerful framework for graph analysis, embedding computation, and machine learning on graph-structured data
Project-URL: Homepage, https://github.com/ashdehghan/NEExT
Project-URL: Documentation, https://neext.readthedocs.io
Project-URL: Repository, https://github.com/ashdehghan/NEExT
Project-URL: Issues, https://github.com/ashdehghan/NEExT/issues
Author-email: Ash Dehghan <ash.dehghan@gmail.com>
Maintainer-email: Ash Dehghan <ash.dehghan@gmail.com>
License: MIT
License-File: LICENSE
Keywords: embedding,graph,graph-ml,machine-learning,network,network-analysis
Classifier: Development Status :: 4 - Beta
Classifier: Intended Audience :: Science/Research
Classifier: License :: OSI Approved :: MIT License
Classifier: Operating System :: OS Independent
Classifier: Programming Language :: Python :: 3
Classifier: Programming Language :: Python :: 3.9
Classifier: Programming Language :: Python :: 3.10
Classifier: Programming Language :: Python :: 3.11
Classifier: Programming Language :: Python :: 3.12
Classifier: Topic :: Scientific/Engineering :: Artificial Intelligence
Classifier: Topic :: Scientific/Engineering :: Information Analysis
Requires-Python: <3.13,>=3.9
Requires-Dist: cairocffi>=1.3.0
Requires-Dist: imbalanced-learn<0.13,>=0.11.0
Requires-Dist: llvmlite>=0.41.0
Requires-Dist: networkx<4,>=3.0
Requires-Dist: numba>=0.58.0
Requires-Dist: numpy<3,>=2.0.0
Requires-Dist: pandas<3,>=2.0.0
Requires-Dist: pydantic>=2.0.0
Requires-Dist: python-igraph>=0.10.0
Requires-Dist: requests>=2.25.0
Requires-Dist: scikit-learn<1.5,>=1.3.0
Requires-Dist: scipy>=1.13.0
Requires-Dist: tqdm>=4.64.0
Requires-Dist: vectorizers<0.3,>=0.2
Requires-Dist: xgboost>=1.7.0
Provides-Extra: advanced
Requires-Dist: matplotlib>=3.5.0; extra == 'advanced'
Requires-Dist: optuna>=3.0.0; extra == 'advanced'
Requires-Dist: plotly>=5.0.0; extra == 'advanced'
Requires-Dist: seaborn>=0.12.0; extra == 'advanced'
Requires-Dist: umap-learn!=0.5.9.post2,>=0.5.7; extra == 'advanced'
Provides-Extra: all
Requires-Dist: black>=23.0.0; extra == 'all'
Requires-Dist: ipykernel>=6.0.0; extra == 'all'
Requires-Dist: isort>=5.12.0; extra == 'all'
Requires-Dist: jupyter>=1.0.0; extra == 'all'
Requires-Dist: matplotlib>=3.5.0; extra == 'all'
Requires-Dist: mypy>=1.0.0; extra == 'all'
Requires-Dist: myst-parser>=2.0.0; extra == 'all'
Requires-Dist: nbsphinx>=0.9.0; extra == 'all'
Requires-Dist: notebook>=7.0.0; extra == 'all'
Requires-Dist: optuna>=3.0.0; extra == 'all'
Requires-Dist: plotly>=5.0.0; extra == 'all'
Requires-Dist: pre-commit>=3.0.0; extra == 'all'
Requires-Dist: pytest-cov>=4.0.0; extra == 'all'
Requires-Dist: pytest-mock>=3.10.0; extra == 'all'
Requires-Dist: pytest>=7.0.0; extra == 'all'
Requires-Dist: ruff>=0.1.0; extra == 'all'
Requires-Dist: seaborn>=0.12.0; extra == 'all'
Requires-Dist: sphinx-autodoc-typehints>=1.25.0; extra == 'all'
Requires-Dist: sphinx-copybutton>=0.5.0; extra == 'all'
Requires-Dist: sphinx-rtd-theme>=1.3.0; extra == 'all'
Requires-Dist: sphinx>=7.0.0; extra == 'all'
Requires-Dist: umap-learn!=0.5.9.post2,>=0.5.7; extra == 'all'
Provides-Extra: dev
Requires-Dist: black>=23.0.0; extra == 'dev'
Requires-Dist: isort>=5.12.0; extra == 'dev'
Requires-Dist: mypy>=1.0.0; extra == 'dev'
Requires-Dist: pre-commit>=3.0.0; extra == 'dev'
Requires-Dist: pytest-cov>=4.0.0; extra == 'dev'
Requires-Dist: pytest-mock>=3.10.0; extra == 'dev'
Requires-Dist: pytest>=7.0.0; extra == 'dev'
Requires-Dist: ruff>=0.1.0; extra == 'dev'
Provides-Extra: docs
Requires-Dist: myst-parser>=2.0.0; extra == 'docs'
Requires-Dist: nbsphinx>=0.9.0; extra == 'docs'
Requires-Dist: sphinx-autodoc-typehints>=1.25.0; extra == 'docs'
Requires-Dist: sphinx-copybutton>=0.5.0; extra == 'docs'
Requires-Dist: sphinx-rtd-theme>=1.3.0; extra == 'docs'
Requires-Dist: sphinx>=7.0.0; extra == 'docs'
Provides-Extra: experiments
Requires-Dist: ipykernel>=6.0.0; extra == 'experiments'
Requires-Dist: jupyter>=1.0.0; extra == 'experiments'
Requires-Dist: notebook>=7.0.0; extra == 'experiments'
